setup.py
emblue/__init__.py
emblue.egg-info/PKG-INFO
emblue.egg-info/SOURCES.txt
emblue.egg-info/dependency_links.txt
emblue.egg-info/not-zip-safe
emblue.egg-info/requires.txt
emblue.egg-info/top_level.txt