Metadata-Version: 1.1
Name: emblue
Version: 1.0
Summary: Utilizar el api de emblue
Home-page: https://github.com/erickhein/emblue
Author: Erick Hein
Author-email: erickhv@gmail.com
License: None
Platform: UNKNOWN
Classifier: Development Status :: 3 - Alpha
Classifier: Intended Audience :: Developers
Classifier: Topic :: Software Development :: Build Tools
Classifier: Programming Language :: Python :: 2.7
